README
setup.py
src/spoj/__init__.py
src/spoj/main.py
src/spoj/settings.py
src/spoj/utils.py
src/spoj.egg-info/PKG-INFO
src/spoj.egg-info/SOURCES.txt
src/spoj.egg-info/dependency_links.txt
src/spoj.egg-info/entry_points.txt
src/spoj.egg-info/not-zip-safe
src/spoj.egg-info/requires.txt
src/spoj.egg-info/top_level.txt
src/spoj/commands/__init__.py
src/spoj/commands/auth.py
src/spoj/commands/desc.py
src/spoj/commands/list.py
src/spoj/commands/status.py
src/spoj/commands/tackle.py