Metadata-Version: 1.1
Name: spoj
Version: 0.0.15
Summary: command line tool for spoj.com 
Home-page: http://github.com/nyamba/spoj
Author: Nyambayar Turbat
Author-email: t.nyambayar@gmail.com
License: BSD
Keywords: spoj spoj.com algorithm
Platform: UNKNOWN
Classifier: Development Status :: 3 - Alpha
Classifier: Topic :: Utilities
Classifier: Topic :: Education
Classifier: License :: OSI Approved :: BSD License
Classifier: Intended Audience :: Customer Service
